COPYING
COPYING.lesser
MANIFEST.in
NOTICE
README.md
requirements.txt
setup.py
compiler/__init__.py
compiler/api/__init__.py
compiler/api/compiler.py
compiler/api/source/auth_key.tl
compiler/api/source/main_api.tl
compiler/api/source/sys_msgs.tl
compiler/api/template/combinator.txt
compiler/api/template/type.txt
compiler/errors/__init__.py
compiler/errors/compiler.py
compiler/errors/sort.py
compiler/errors/source/303_SEE_OTHER.tsv
compiler/errors/source/400_BAD_REQUEST.tsv
compiler/errors/source/401_UNAUTHORIZED.tsv
compiler/errors/source/403_FORBIDDEN.tsv
compiler/errors/source/406_NOT_ACCEPTABLE.tsv
compiler/errors/source/420_FLOOD.tsv
compiler/errors/source/500_INTERNAL_SERVER_ERROR.tsv
compiler/errors/source/503_SERVICE_UNAVAILABLE.tsv
compiler/errors/template/class.txt
compiler/errors/template/sub_class.txt
pyroherd/__init__.py
pyroherd/client.py
pyroherd/dispatcher.py
pyroherd/emoji.py
pyroherd/file_id.py
pyroherd/filters.py
pyroherd/mime_types.py
pyroherd/py.typed
pyroherd/qrlogin.py
pyroherd/sync.py
pyroherd/utils.py
pyroherd.egg-info/PKG-INFO
pyroherd.egg-info/SOURCES.txt
pyroherd.egg-info/dependency_links.txt
pyroherd.egg-info/not-zip-safe
pyroherd.egg-info/requires.txt
pyroherd.egg-info/top_level.txt
pyroherd/connection/__init__.py
pyroherd/connection/connection.py
pyroherd/connection/transport/__init__.py
pyroherd/connection/transport/tcp/__init__.py
pyroherd/connection/transport/tcp/tcp.py
pyroherd/connection/transport/tcp/tcp_abridged.py
pyroherd/connection/transport/tcp/tcp_abridged_o.py
pyroherd/connection/transport/tcp/tcp_full.py
pyroherd/connection/transport/tcp/tcp_intermediate.py
pyroherd/connection/transport/tcp/tcp_intermediate_o.py
pyroherd/crypto/__init__.py
pyroherd/crypto/aes.py
pyroherd/crypto/mtproto.py
pyroherd/crypto/prime.py
pyroherd/crypto/rsa.py
pyroherd/enums/__init__.py
pyroherd/enums/auto_name.py
pyroherd/enums/business_schedule.py
pyroherd/enums/chat_action.py
pyroherd/enums/chat_event_action.py
pyroherd/enums/chat_join_type.py
pyroherd/enums/chat_member_status.py
pyroherd/enums/chat_members_filter.py
pyroherd/enums/chat_type.py
pyroherd/enums/client_platform.py
pyroherd/enums/folder_color.py
